{"cameraMode":{"drawMode":0,"name":"Shaded","section":"Shading Mode"},"sceneLighting":false,"audioPlay":false,"sceneViewState":{"m_AlwaysRefresh":false,"showFog":true,"showSkybox":false,"showFlares":true,"showImageEffects":true,"showParticleSystems":true,"showVisualEffectGraphs":true,"m_FxEnabled":true},"in2DMode":false,"pivot":{"x":-0.948521077632904,"y":4.247727870941162,"z":4.7698974609375},"rotation":{"x":0.09837500005960465,"y":0.05337612330913544,"z":0.004571155644953251,"w":-0.9942662119865418},"size":6.307333946228027,"orthographic":false}